{"type": "FeatureCollection", "name": "stops", "crs": {"type": "name", "properties": {"name": "urn:ogc:def:crs:OGC:1.3:CRS84"}}, "features": [{"type": "Feature", "properties": {"stop_id": "1_01", "stop_name": "岡崎", "zone_id": "1_01", "location_type": "0"}, "geometry": {"type": "Point", "coordinates": [134.61718, 34.18527]}}, {"type": "Feature", "properties": {"stop_id": "2_01", "stop_name": "土佐泊", "zone_id": "2_01", "location_type": "0"}, "geometry": {"type": "Point", "coordinates": [134.62076, 34.18823]}}, {"type": "Feature", "properties": {"stop_id": "3_01", "stop_name": "黒崎", "zone_id": "3_01", "location_type": "0"}, "geometry": {"type": "Point", "coordinates": [134.5971, 34.19477]}}, {"type": "Feature", "properties": {"stop_id": "4_01", "stop_name": "高島", "zone_id": "4_01", "location_type": "0"}, "geometry": {"type": "Point", "coordinates": [134.59792, 34.19854]}}, {"type": "Feature", "properties": {"stop_id": "5_01", "stop_name": "島田", "zone_id": "5_01", "location_type": "0"}, "geometry": {"type": "Point", "coordinates": [134.59318, 34.22561]}}, {"type": "Feature", "properties": {"stop_id": "6_01", "stop_name": "堂浦", "zone_id": "6_01", "location_type": "0"}, "geometry": {"type": "Point", "coordinates": [134.59037, 34.22416]}}]}